dataweaver.py
dataweaver_ai-1.0.0.dist-info/licenses/LICENSE
dataweaver_ai-1.0.0.dist-info/METADATA
dataweaver_ai-1.0.0.dist-info/WHEEL
dataweaver_ai-1.0.0.dist-info/top_level.txt
dataweaver_ai-1.0.0.dist-info/RECORD
