Metadata-Version: 2.4
Name: dataweaver-ai
Version: 1.0.0
Summary: Revolutionary Resonance Learning - Discover patterns between patterns through multi-dimensional harmonics
Home-page: https://github.com/fiafghan/DataWeaver
Author: Fardin Ibrahimi
Author-email: Fardin Ibrahimi <fiafghan@example.com>
License: MIT
Project-URL: Homepage, https://github.com/fiafghan/DataWeaver
Project-URL: Documentation, https://github.com/fiafghan/DataWeaver/blob/main/DATAWEAVER_WHITEPAPER.md
Project-URL: Repository, https://github.com/fiafghan/DataWeaver
Project-URL: Bug Tracker, https://github.com/fiafghan/DataWeaver/issues
Keywords: machine-learning,deep-learning,resonance-learning,pattern-recognition,neural-networks,pytorch,multi-view-learning,data-science
Classifier: Development Status :: 4 - Beta
Classifier: Intended Audience :: Developers
Classifier: Intended Audience :: Science/Research
Classifier: License :: OSI Approved :: MIT License
Classifier: Programming Language :: Python :: 3
Classifier: Programming Language :: Python :: 3.8
Classifier: Programming Language :: Python :: 3.9
Classifier: Programming Language :: Python :: 3.10
Classifier: Programming Language :: Python :: 3.11
Classifier: Programming Language :: Python :: 3.12
Classifier: Topic :: Scientific/Engineering :: Artificial Intelligence
Requires-Python: >=3.8
License-File: LICENSE
Requires-Dist: torch>=2.0.0
Requires-Dist: numpy>=1.21.0
Requires-Dist: scikit-learn>=1.0.0
Provides-Extra: dev
Requires-Dist: pytest>=7.0.0; extra == "dev"
Requires-Dist: pytest-cov>=4.0.0; extra == "dev"
Requires-Dist: black>=23.0.0; extra == "dev"
Requires-Dist: flake8>=6.0.0; extra == "dev"
Provides-Extra: viz
Requires-Dist: matplotlib>=3.5.0; extra == "viz"
Dynamic: author
Dynamic: home-page
Dynamic: license-file
Dynamic: requires-python
